CHANGES.rst
LICENSE.txt
MANIFEST.in
README.rst
setup.cfg
setup.py
GreenRocket.egg-info/PKG-INFO
GreenRocket.egg-info/SOURCES.txt
GreenRocket.egg-info/dependency_links.txt
GreenRocket.egg-info/top_level.txt
GreenRocket.egg-info/zip-safe
greenrocket/__init__.py
greenrocket/aio.py