Metadata-Version: 1.1
Name: GreenRocket
Version: 0.30
Summary: A simple and compact implementation of Observer design pattern
Home-page: https://bitbucket.org/kr41/greenrocket
Author: Dmitry Vakhrushev
Author-email: self@kr41.net
License: BSD
Download-URL: https://bitbucket.org/kr41/greenrocket/downloads
Keywords: signal observer publisher subscriber asyncio
Platform: UNKNOWN
Classifier: License :: OSI Approved :: BSD License
Classifier: Programming Language :: Python
Classifier: Programming Language :: Python :: 2.7
Classifier: Programming Language :: Python :: 3.3
Classifier: Programming Language :: Python :: 3.4
Classifier: Programming Language :: Python :: 3.5
Classifier: Programming Language :: Python :: Implementation :: PyPy
Classifier: Programming Language :: Python :: Implementation :: CPython
Classifier: Topic :: Software Development :: Libraries :: Python Modules
Classifier: Intended Audience :: Developers
Classifier: Operating System :: OS Independent
